README.rst
setup.py
wishbone/__init__.py
wishbone/actor.py
wishbone/actorconfig.py
wishbone/bootstrap.py
wishbone/componentmanager.py
wishbone/error.py
wishbone/event.py
wishbone/logging.py
wishbone/modulemanager.py
wishbone/moduletype.py
wishbone/queue.py
wishbone.egg-info/PKG-INFO
wishbone.egg-info/SOURCES.txt
wishbone.egg-info/dependency_links.txt
wishbone.egg-info/entry_points.txt
wishbone.egg-info/namespace_packages.txt
wishbone.egg-info/not-zip-safe
wishbone.egg-info/requires.txt
wishbone.egg-info/top_level.txt
wishbone/config/__init__.py
wishbone/config/configfile.py
wishbone/config/schema.py
wishbone/data/banner.tmpl
wishbone/data/wordlist.txt
wishbone/function/__init__.py
wishbone/function/module/__init__.py
wishbone/function/module/append.py
wishbone/function/module/lowercase.py
wishbone/function/module/set.py
wishbone/function/module/uppercase.py
wishbone/function/template/__init__.py
wishbone/function/template/choice.py
wishbone/function/template/cycle.py
wishbone/function/template/environment.py
wishbone/function/template/epoch.py
wishbone/function/template/pid.py
wishbone/function/template/random_bool.py
wishbone/function/template/random_integer.py
wishbone/function/template/random_uuid.py
wishbone/function/template/random_word.py
wishbone/function/template/regex.py
wishbone/function/template/strftime.py
wishbone/function/template/version.py
wishbone/module/__init__.py
wishbone/module/acknowledge.py
wishbone/module/count.py
wishbone/module/cron.py
wishbone/module/dictgenerator.py
wishbone/module/fanout.py
wishbone/module/fileout.py
wishbone/module/fresh.py
wishbone/module/funnel.py
wishbone/module/generator.py
wishbone/module/modify.py
wishbone/module/null.py
wishbone/module/pack.py
wishbone/module/queueselect.py
wishbone/module/roundrobin.py
wishbone/module/stdout.py
wishbone/module/switch.py
wishbone/module/template.py
wishbone/module/testevent.py
wishbone/module/throughput.py
wishbone/module/tippingbucket.py
wishbone/module/ttl.py
wishbone/module/unpack.py
wishbone/module/wb_inotify.py
wishbone/module/wbsyslog.py
wishbone/protocol/__init__.py
wishbone/protocol/decode/__init__.py
wishbone/protocol/decode/dummy.py
wishbone/protocol/decode/json.py
wishbone/protocol/decode/msgpack.py
