Metadata-Version: 1.1
Name: wishbone
Version: 3.1.2
Summary: Build composable event pipeline servers with minimal effort.
Home-page: https://github.com/smetj/wishbone
Author: Jelle Smet
Author-email: development@smetj.net
License: UNKNOWN
Download-URL: https://github.com/smetj/wishbone/tarball/master
Platform: Linux
Classifier: Development Status :: 5 - Production/Stable
Classifier: License :: OSI Approved :: GNU General Public License v3 or later (GPLv3+)
Classifier: Programming Language :: Python
Classifier: Programming Language :: Python :: 3
Classifier: Programming Language :: Python :: Implementation :: PyPy
Classifier: Intended Audience :: Developers
Classifier: Intended Audience :: System Administrators
